{
  "graphic": [
    {
      "id": "graphic-1",
      "title": "Echo Festival",
      "category": "Poster",
      "description": "Festival branding and poster design",
      "image": "https://images.unsplash.com/photo-1561070791-2526d30994b5?w=600&q=80",
      "tools": ["Adobe Illustrator", "Figma"],
      "overview": "A vibrant festival poster design that captures the energy and excitement of the Echo Festival.",
      "process": [
        {
          "step": 1,
          "title": "Research & Concept",
          "description": "Researched festival themes, audience demographics, and visual trends. Developed initial mood boards and color palettes to match the festival's energy."
        },
        {
          "step": 2,
          "title": "Design Iteration",
          "description": "Created multiple poster variations with different typography treatments and layouts. Tested color combinations and visual hierarchy."
        },
        {
          "step": 3,
          "title": "Refinement",
          "description": "Refined the winning design based on feedback. Enhanced typography, adjusted spacing, and optimized for both digital and print formats."
        }
      ],
      "projectImages": [
        "https://images.unsplash.com/photo-1561070791-2526d30994b5?w=600&q=80",
        "https://images.unsplash.com/photo-1561070791-2526d30994b5?w=600&q=80",
        "https://images.unsplash.com/photo-1561070791-2526d30994b5?w=600&q=80"
      ]
    },
    {
      "id": "graphic-2",
      "title": "Mori Studio",
      "category": "Branding",
      "description": "Complete brand identity system",
      "image": "https://images.unsplash.com/photo-1561070791-2526d30994b5?w=600&q=80",
      "tools": ["Adobe InDesign", "Illustrator", "Figma"],
      "overview": "A comprehensive brand identity system for a modern design studio including logo, color palette, and brand guidelines.",
      "process": [
        {
          "step": 1,
          "title": "Brand Strategy",
          "description": "Conducted stakeholder interviews and competitor analysis. Defined brand values, mission, and target audience."
        },
        {
          "step": 2,
          "title": "Logo Design",
          "description": "Explored 50+ logo concepts focusing on minimalism and elegance. Tested logos across different scales and applications."
        },
        {
          "step": 3,
          "title": "Brand System",
          "description": "Created comprehensive brand guidelines including typography, color system, imagery style, and usage patterns."
        }
      ],
      "projectImages": [
        "https://images.unsplash.com/photo-1561070791-2526d30994b5?w=600&q=80",
        "https://images.unsplash.com/photo-1561070791-2526d30994b5?w=600&q=80"
      ]
    },
    {
      "id": "graphic-3",
      "title": "Issue No.12",
      "category": "Editorial",
      "description": "Magazine layout and typography",
      "image": "https://images.unsplash.com/photo-1561070791-2526d30994b5?w=600&q=80",
      "tools": ["Adobe InDesign", "Illustrator"],
      "overview": "A quarterly magazine publication featuring compelling editorial design and sophisticated typography.",
      "process": [
        {
          "step": 1,
          "title": "Content Planning",
          "description": "Reviewed editorial content and developed a clear information hierarchy. Created wireframes for all page templates."
        },
        {
          "step": 2,
          "title": "Layout Design",
          "description": "Designed page layouts with focus on readability and visual balance. Developed modular system for consistent design."
        },
        {
          "step": 3,
          "title": "Final Production",
          "description": "Prepared files for print production. Optimized typography and ensured color accuracy across all pages."
        }
      ],
      "projectImages": [
        "https://images.unsplash.com/photo-1561070791-2526d30994b5?w=600&q=80"
      ]
    },
    {
      "id": "graphic-4",
      "title": "Drift Campaign",
      "category": "Campaign",
      "description": "Marketing campaign visual design",
      "image": "https://images.unsplash.com/photo-1561070791-2526d30994b5?w=600&q=80",
      "tools": ["Adobe Creative Suite"],
      "overview": "A comprehensive marketing campaign with consistent visual language across multiple touchpoints.",
      "process": [
        {
          "step": 1,
          "title": "Campaign Concept",
          "description": "Developed campaign theme and key messaging. Created visual mood boards for the entire campaign."
        },
        {
          "step": 2,
          "title": "Asset Creation",
          "description": "Designed all campaign assets including social media graphics, banners, and promotional materials."
        },
        {
          "step": 3,
          "title": "Implementation",
          "description": "Ensured consistent application across all channels. Optimized assets for various platforms and screen sizes."
        }
      ],
      "projectImages": [
        "https://images.unsplash.com/photo-1561070791-2526d30994b5?w=600&q=80"
      ]
    },
    {
      "id": "graphic-5",
      "title": "Type Specimen",
      "category": "Typography",
      "description": "Custom typeface design",
      "image": "https://images.unsplash.com/photo-1561070791-2526d30994b5?w=600&q=80",
      "tools": ["Glyphs", "Adobe Illustrator"],
      "overview": "A complete typeface family specimen book showcasing a custom-designed font with multiple weights and styles.",
      "process": [
        {
          "step": 1,
          "title": "Typeface Concept",
          "description": "Defined typeface personality and design principles. Sketched initial letterforms and established baseline system."
        },
        {
          "step": 2,
          "title": "Glyph Development",
          "description": "Drew and refined individual glyphs for consistency. Created multiple weights and styles for the typeface family."
        },
        {
          "step": 3,
          "title": "Specimen Design",
          "description": "Created comprehensive specimen book showcasing the typeface in real-world applications."
        }
      ],
      "projectImages": [
        "https://images.unsplash.com/photo-1561070791-2526d30994b5?w=600&q=80"
      ]
    },
    {
      "id": "graphic-6",
      "title": "Nocturne LP",
      "category": "Album",
      "description": "Album artwork and packaging",
      "image": "https://images.unsplash.com/photo-1561070791-2526d30994b5?w=600&q=80",
      "tools": ["Adobe Photoshop", "Illustrator"],
      "overview": "A complete album package design including cover art, booklet, and digital artwork for a music release.",
      "process": [
        {
          "step": 1,
          "title": "Concept Development",
          "description": "Listened to the album and developed visual concepts that reflect the music's mood and themes."
        },
        {
          "step": 2,
          "title": "Cover Design",
          "description": "Created striking cover artwork with typography and imagery that captures the album's essence."
        },
        {
          "step": 3,
          "title": "Package Design",
          "description": "Designed complete packaging including booklet layout, back cover, and disc artwork."
        }
      ],
      "projectImages": [
        "https://images.unsplash.com/photo-1561070791-2526d30994b5?w=600&q=80"
      ]
    }
  ],
  "3d": [
    {
      "id": "3d-1",
      "title": "Sphere Study",
      "category": "Blender",
      "description": "3D sphere rendering study",
      "image": "https://images.unsplash.com/photo-1561070791-2526d30994b5?w=600&q=80",
      "tools": ["Blender", "Cycles Render"],
      "overview": "A detailed study in 3D rendering focusing on material properties, lighting, and photorealism.",
      "process": [
        {
          "step": 1,
          "title": "Modeling",
          "description": "Created base sphere geometry and applied high-poly subdivisions for smooth surfaces."
        },
        {
          "step": 2,
          "title": "Material Creation",
          "description": "Developed realistic material shaders with proper roughness, metallic, and reflection properties."
        },
        {
          "step": 3,
          "title": "Lighting & Rendering",
          "description": "Set up 3-point lighting setup and rendered with Cycles for photorealistic output."
        }
      ],
      "projectImages": [
        "https://images.unsplash.com/photo-1561070791-2526d30994b5?w=600&q=80"
      ]
    },
    {
      "id": "3d-2",
      "title": "Sand Pavilion",
      "category": "Cinema 4D",
      "description": "Architectural visualization",
      "image": "https://images.unsplash.com/photo-1561070791-2526d30994b5?w=600&q=80",
      "tools": ["Cinema 4D", "Octane Render"],
      "overview": "A stunning architectural visualization of a modern pavilion design with landscape integration.",
      "process": [
        {
          "step": 1,
          "title": "Architectural Modeling",
          "description": "Built detailed 3D model of the pavilion structure based on architectural plans."
        },
        {
          "step": 2,
          "title": "Environment Design",
          "description": "Created surrounding landscape, terrain, and vegetation for context."
        },
        {
          "step": 3,
          "title": "Lighting & Rendering",
          "description": "Applied realistic lighting to show the design in different times of day and rendered final images."
        }
      ],
      "projectImages": [
        "https://images.unsplash.com/photo-1561070791-2526d30994b5?w=600&q=80"
      ]
    },
    {
      "id": "3d-3",
      "title": "Crystal 01",
      "category": "3D Model",
      "description": "Crystal formation render",
      "image": "https://images.unsplash.com/photo-1561070791-2526d30994b5?w=600&q=80",
      "tools": ["Blender"],
      "overview": "An artistic exploration of crystalline structures using advanced materials and rendering techniques.",
      "process": [
        {
          "step": 1,
          "title": "Geometry Sculpting",
          "description": "Sculpted organic crystal shapes with attention to natural geometric patterns."
        },
        {
          "step": 2,
          "title": "Material Development",
          "description": "Created translucent glass materials with proper refraction and light dispersion."
        },
        {
          "step": 3,
          "title": "Final Render",
          "description": "Rendered with volumetric lighting to showcase the crystal's transparency and internal light play."
        }
      ],
      "projectImages": [
        "https://images.unsplash.com/photo-1561070791-2526d30994b5?w=600&q=80"
      ]
    },
    {
      "id": "3d-4",
      "title": "Dusk Set",
      "category": "Octane",
      "description": "Octane render composition",
      "image": "https://images.unsplash.com/photo-1561070791-2526d30994b5?w=600&q=80",
      "tools": ["Cinema 4D", "Octane Render"],
      "overview": "A cinematic composition combining multiple 3D elements with dramatic lighting during sunset.",
      "process": [
        {
          "step": 1,
          "title": "Scene Composition",
          "description": "Arranged 3D models and props to create dynamic composition with strong visual flow."
        },
        {
          "step": 2,
          "title": "Lighting Design",
          "description": "Implemented sunset lighting with warm tones and dramatic shadows for cinematic feel."
        },
        {
          "step": 3,
          "title": "Post-Production",
          "description": "Enhanced final render with color grading and subtle effects in post-production."
        }
      ],
      "projectImages": [
        "https://images.unsplash.com/photo-1561070791-2526d30994b5?w=600&q=80"
      ]
    },
    {
      "id": "3d-5",
      "title": "Inflate Type",
      "category": "Typography",
      "description": "3D inflatable typography",
      "image": "https://images.unsplash.com/photo-1561070791-2526d30994b5?w=600&q=80",
      "tools": ["Blender", "Geometry Nodes"],
      "overview": "Playful 3D typography exploring inflatable balloon aesthetics and fluid dynamics.",
      "process": [
        {
          "step": 1,
          "title": "Type Modeling",
          "description": "Modeled 3D typeface geometry and applied soft body simulation for inflatable effect."
        },
        {
          "step": 2,
          "title": "Material & Shading",
          "description": "Created glossy balloon materials with specular highlights and proper light reflection."
        },
        {
          "step": 3,
          "title": "Animation & Rendering",
          "description": "Rendered multiple frames showing the inflatable type in motion and final static composition."
        }
      ],
      "projectImages": [
        "https://images.unsplash.com/photo-1561070791-2526d30994b5?w=600&q=80"
      ]
    },
    {
      "id": "3d-6",
      "title": "Moss Study",
      "category": "Texture",
      "description": "Organic moss texture study",
      "image": "https://images.unsplash.com/photo-1561070791-2526d30994b5?w=600&q=80",
      "tools": ["Blender", "Substance Painter"],
      "overview": "A detailed study in creating realistic organic surface textures with procedural methods.",
      "process": [
        {
          "step": 1,
          "title": "Texture Baking",
          "description": "Created high-poly moss geometry and baked textures for detail preservation."
        },
        {
          "step": 2,
          "title": "Shader Network",
          "description": "Built complex shader network combining multiple textures for realistic moss appearance."
        },
        {
          "step": 3,
          "title": "Final Render",
          "description": "Rendered with subsurface scattering to show organic light transmission through moss."
        }
      ],
      "projectImages": [
        "https://images.unsplash.com/photo-1561070791-2526d30994b5?w=600&q=80"
      ]
    }
  ],
  "animation": [
    {
      "id": "animation-1",
      "title": "Spin Cycle",
      "category": "Loop",
      "description": "Rotating motion design loop",
      "image": "https://images.unsplash.com/photo-1561070791-2526d30994b5?w=600&q=80",
      "tools": ["After Effects"],
      "overview": "A mesmerizing looping animation featuring rotating geometric shapes with smooth easing.",
      "process": [
        {
          "step": 1,
          "title": "Concept & Storyboard",
          "description": "Sketched animation concepts and created visual storyboards for the loop animation."
        },
        {
          "step": 2,
          "title": "Animation",
          "description": "Animated geometric shapes with careful easing curves for smooth, natural motion."
        },
        {
          "step": 3,
          "title": "Effects & Rendering",
          "description": "Added particle effects and motion blur for enhanced visual polish."
        }
      ],
      "projectImages": [
        "https://images.unsplash.com/photo-1561070791-2526d30994b5?w=600&q=80"
      ]
    },
    {
      "id": "animation-2",
      "title": "Rise Logo",
      "category": "Logo Animation",
      "description": "Logo rise and bounce animation",
      "image": "https://images.unsplash.com/photo-1561070791-2526d30994b5?w=600&q=80",
      "tools": ["After Effects", "Cinema 4D"],
      "overview": "A dynamic logo animation with bouncy physics and smooth transitions perfect for branding.",
      "process": [
        {
          "step": 1,
          "title": "Logo Design",
          "description": "Designed the logo and prepared all assets for animation in layered format."
        },
        {
          "step": 2,
          "title": "Animation",
          "description": "Created bounce animation using physics-based easing. Built smooth entrance and exit sequences."
        },
        {
          "step": 3,
          "title": "Polish",
          "description": "Added subtle details like glows and shadows to enhance the animation."
        }
      ],
      "projectImages": [
        "https://images.unsplash.com/photo-1561070791-2526d30994b5?w=600&q=80"
      ]
    },
    {
      "id": "animation-3",
      "title": "Flow/Type",
      "category": "Kinetic",
      "description": "Kinetic typography motion",
      "image": "https://images.unsplash.com/photo-1561070791-2526d30994b5?w=600&q=80",
      "tools": ["After Effects"],
      "overview": "Expressive kinetic typography with fluid motion bringing text to life.",
      "process": [
        {
          "step": 1,
          "title": "Typography",
          "description": "Selected and styled typeface to support the motion design concept."
        },
        {
          "step": 2,
          "title": "Motion Design",
          "description": "Animated individual letters with flowing, organic motion paths."
        },
        {
          "step": 3,
          "title": "Sound Design",
          "description": "Synced animation with audio for a cohesive audiovisual experience."
        }
      ],
      "projectImages": [
        "https://images.unsplash.com/photo-1561070791-2526d30994b5?w=600&q=80"
      ]
    },
    {
      "id": "animation-4",
      "title": "Pulse",
      "category": "Abstract",
      "description": "Pulsing abstract animation",
      "image": "https://images.unsplash.com/photo-1561070791-2526d30994b5?w=600&q=80",
      "tools": ["After Effects"],
      "overview": "An abstract animation exploring rhythm and repetition with hypnotic pulsing elements.",
      "process": [
        {
          "step": 1,
          "title": "Concept Development",
          "description": "Explored abstract concepts and created multiple visual variations."
        },
        {
          "step": 2,
          "title": "Animation",
          "description": "Created rhythmic pulsing animations synced to an underlying beat."
        },
        {
          "step": 3,
          "title": "Color & Effects",
          "description": "Applied color grading and effects to enhance the hypnotic quality."
        }
      ],
      "projectImages": [
        "https://images.unsplash.com/photo-1561070791-2526d30994b5?w=600&q=80"
      ]
    },
    {
      "id": "animation-5",
      "title": "Ember",
      "category": "Particle",
      "description": "Ember particle effects",
      "image": "https://images.unsplash.com/photo-1561070791-2526d30994b5?w=600&q=80",
      "tools": ["After Effects", "Particular"],
      "overview": "A beautiful particle animation creating the effect of floating embers and magical particles.",
      "process": [
        {
          "step": 1,
          "title": "Particle System",
          "description": "Built custom particle system with careful velocity and lifetime settings."
        },
        {
          "step": 2,
          "title": "Physics",
          "description": "Applied gravity and air resistance for realistic floating behavior."
        },
        {
          "step": 3,
          "title": "Lighting",
          "description": "Added glows and lighting effects to make particles feel luminous and magical."
        }
      ],
      "projectImages": [
        "https://images.unsplash.com/photo-1561070791-2526d30994b5?w=600&q=80"
      ]
    },
    {
      "id": "animation-6",
      "title": "Plus Loop",
      "category": "Symbol",
      "description": "Plus symbol loop animation",
      "image": "https://images.unsplash.com/photo-1561070791-2526d30994b5?w=600&q=80",
      "tools": ["After Effects"],
      "overview": "A simple yet elegant animation of a plus symbol rotating and transforming in a seamless loop.",
      "process": [
        {
          "step": 1,
          "title": "Shape Design",
          "description": "Created geometric plus shape with precise proportions for animation."
        },
        {
          "step": 2,
          "title": "Looping Animation",
          "description": "Built seamless loop animation with smooth rotation and scaling."
        },
        {
          "step": 3,
          "title": "Timing",
          "description": "Fine-tuned animation timing for perfect loop point and natural motion flow."
        }
      ],
      "projectImages": [
        "https://images.unsplash.com/photo-1561070791-2526d30994b5?w=600&q=80"
      ]
    }
  ]
}
